semroute/__init__.py
semroute/semroute.py
semroute/embedders/__init__.py
semroute/embedders/base.py
semroute/embedders/custom.py
semroute/embedders/mistral.py
semroute/embedders/openai.py
semroute/utils/__init__.py
semroute/utils/centroid.py
semroute/utils/similar_utterances.py
semroute/utils/similarity.py
tests/__init__.py
semroute-1.0.1.dist-info/LICENSE
semroute-1.0.1.dist-info/METADATA
semroute-1.0.1.dist-info/WHEEL
semroute-1.0.1.dist-info/top_level.txt
semroute-1.0.1.dist-info/RECORD
